{"chunk_definitions":[{"chunk_id":"csetup_chunk","chunk_label":"setup","document_id":"67D7BE1","expansion_state":0,"options":{"engine":"r","include":false,"label":"setup"},"row":15,"row_count":1,"visible":true},{"chunk_id":"cwzidyhv7a4um","chunk_label":"library","document_id":"67D7BE1","expansion_state":0,"options":{"engine":"r","include":false,"label":"library"},"row":35,"row_count":1,"visible":true},{"chunk_id":"cdnpg0kpnj4f1","chunk_label":"import data","document_id":"67D7BE1","expansion_state":0,"options":{"engine":"r","include":false,"label":"import data"},"row":41,"row_count":1,"visible":true},{"chunk_id":"c24q1lp1xz149","chunk_label":"os_experience_figure","document_id":"67D7BE1","expansion_state":0,"options":{"echo":false,"engine":"r","label":"os_experience_figure","warning":true},"row":111,"row_count":1,"visible":true}],"chunk_rendered_width":640,"default_chunk_options":{"echo":true},"doc_write_time":1579771686,"working_dir":null}